kiirastuli/__init__.py
kiirastuli/__main__.py
kiirastuli/cli.py
kiirastuli/kiirastuli.py
kiirastuli-2023.10.21.dist-info/LICENSE
kiirastuli-2023.10.21.dist-info/METADATA
kiirastuli-2023.10.21.dist-info/WHEEL
kiirastuli-2023.10.21.dist-info/entry_points.txt
kiirastuli-2023.10.21.dist-info/top_level.txt
kiirastuli-2023.10.21.dist-info/RECORD
