Metadata-Version: 2.1
Name: kiirastuli
Version: 2023.10.21
Summary: Purgatory (Finnish: kiirastuli) - purge like hell to stay out of trouble.
Author-email: Stefan Hagen <stefan@hagen.link>
Maintainer-email: Stefan Hagen <stefan@hagen.link>
Project-URL: Homepage, https://git.sr.ht/~sthagen/kiirastuli
Project-URL: Bug-Tracker, https://todo.sr.ht/~sthagen/kiirastuli
Project-URL: Documentation, https://codes.dilettant.life/docs/kiirastuli
Project-URL: Source-Code, https://git.sr.ht/~sthagen/kiirastuli
Project-URL: Test-Coverage, https://codes.dilettant.life/coverage/kiirastuli
Keywords: developer-tools,file-system,validation,verification
Classifier: Development Status :: 3 - Alpha
Classifier: Intended Audience :: Developers
Classifier: License :: OSI Approved :: MIT License
Classifier: Programming Language :: Python :: 3.10
Classifier: Programming Language :: Python :: 3.11
Classifier: Programming Language :: Python :: 3.9
Requires-Python: >=3.9
License-File: LICENSE
Requires-Dist: puhdistusalue >=2022.7.24
Requires-Dist: scooby >=0.9.2
Requires-Dist: typer >=0.9.0
Provides-Extra: dev
Requires-Dist: black ; extra == 'dev'
Requires-Dist: coverage ; extra == 'dev'
Requires-Dist: hypothesis ; extra == 'dev'
Requires-Dist: mypy ; extra == 'dev'
Requires-Dist: pytest ; extra == 'dev'
Requires-Dist: pytest-cov ; extra == 'dev'
Requires-Dist: pytest-flake8 ; extra == 'dev'
Requires-Dist: ruff ; extra == 'dev'
